bubs/__init__.py
bubs/char_to_int.py
bubs/embedding_layer.py
bubs/helpers.py
bubs/tokenizer.py
bubs/tests/__init__.py
bubs/tests/dummy_weights.npz
bubs/tests/test_embedding_layer.py
bubs/tests/test_helpers.py
bubs/tests/test_tokenizer.py
bubs-0.1.0.dist-info/AUTHORS.md
bubs-0.1.0.dist-info/LICENSE
bubs-0.1.0.dist-info/METADATA
bubs-0.1.0.dist-info/WHEEL
bubs-0.1.0.dist-info/top_level.txt
bubs-0.1.0.dist-info/RECORD
