Metadata-Version: 2.1
Name: bubs
Version: 0.1.0
Summary: Keras Implementation of Flair's Contextualized Embeddings
Home-page: https://github.com/kensho-technologies/bubs
Author: Kensho Technologies, LLC.
Author-email: bubsr@kensho.com
License: Apache 2.0
Platform: UNKNOWN
Requires-Dist: funcy (>=1.10)
Requires-Dist: numpy (>=1.10.0)
Requires-Dist: segtok (>=1.5.7)
Requires-Dist: tensorflow (>=1.13)
